hyperrag/__init__.py
hyperrag-0.0.1.dist-info/licenses/LICENSE
hyperrag-0.0.1.dist-info/METADATA
hyperrag-0.0.1.dist-info/WHEEL
hyperrag-0.0.1.dist-info/top_level.txt
hyperrag-0.0.1.dist-info/RECORD
