Metadata-Version: 2.4
Name: hyperrag
Version: 0.0.1
Summary: Reserved package name for future project
Author: Your Name
License: Apache-2.0
Requires-Python: >=3.10
License-File: LICENSE
Requires-Dist: build>=1.3.0
Requires-Dist: twine>=6.2.0
Dynamic: license-file
